pretty_jupyter/__init__.py
pretty_jupyter/__main__.py
pretty_jupyter/console.py
pretty_jupyter/constants.py
pretty_jupyter/magics.py
pretty_jupyter/testing.py
pretty_jupyter/tokens.py
pretty_jupyter/utils.py
pretty_jupyter/config/metadata/cell_spec.yaml
pretty_jupyter/config/metadata/nb_defaults.yaml
pretty_jupyter/config/metadata/nb_spec.yaml
pretty_jupyter/helpers/__init__.py
pretty_jupyter/helpers/matplotlib.py
pretty_jupyter/preprocessors/__init__.py
pretty_jupyter/preprocessors/_metadata_preprocessor.py
pretty_jupyter/preprocessors/_token_preprocessor.py
pretty_jupyter/quickstart/empty.ipynb
pretty_jupyter/templates/pj/base.html.j2
pretty_jupyter/templates/pj/conf.json
pretty_jupyter/templates/pj/index.html.j2
pretty_jupyter/templates/pj/static/pj-tabset.css
pretty_jupyter/templates/pj/static/pj-toc.css
pretty_jupyter/templates/pj/static/pj.css
pretty_jupyter/templates/pj/static/pj.js
pretty_jupyter/templates/pj/static/libs/bootstrap.min.js
pretty_jupyter/templates/pj/static/libs/jquery-ui.min.js
pretty_jupyter/templates/pj/static/libs/jquery.min.js
pretty_jupyter/templates/pj/static/libs/jquery.stickytabs.js
pretty_jupyter/templates/pj/static/libs/jquery.tocify.css
pretty_jupyter/templates/pj/static/libs/jquery.tocify.js
pretty_jupyter/templates/pj/static/libs/plotly.min.js
pretty_jupyter/templates/pj/static/libs/require.min.js
pretty_jupyter/templates/pj/static/themes/bootstrap.css
pretty_jupyter/templates/pj/static/themes/cerulean.css
pretty_jupyter/templates/pj/static/themes/cosmo.css
pretty_jupyter/templates/pj/static/themes/cyborg.css
pretty_jupyter/templates/pj/static/themes/darkly.css
pretty_jupyter/templates/pj/static/themes/flatly.css
pretty_jupyter/templates/pj/static/themes/journal.css
pretty_jupyter/templates/pj/static/themes/lumen.css
pretty_jupyter/templates/pj/static/themes/paper.css
pretty_jupyter/templates/pj/static/themes/readable.css
pretty_jupyter/templates/pj/static/themes/sandstone.css
pretty_jupyter-2.0.8.dist-info/LICENSE.md
pretty_jupyter-2.0.8.dist-info/METADATA
pretty_jupyter-2.0.8.dist-info/WHEEL
pretty_jupyter-2.0.8.dist-info/entry_points.txt
pretty_jupyter-2.0.8.dist-info/top_level.txt
pretty_jupyter-2.0.8.dist-info/RECORD
