Metadata-Version: 2.1
Name: pretty-jupyter
Version: 2.0.8
Summary: Exports Jupyter notebook into beautiful and dynamic HTML report.
Author: Jan Palasek
License:                       GNU GENERAL PUBLIC LICENSE
Project-URL: Source, https://github.com/JanPalasek/pretty-jupyter
Project-URL: Bug Tracker, https://github.com/JanPalasek/pretty-jupyter/issues
Project-URL: CI, https://github.com/JanPalasek/pretty-jupyter/actions
Classifier: Development Status :: 5 - Production/Stable
Classifier: Framework :: Jupyter
Classifier: Intended Audience :: Developers
Classifier: Intended Audience :: Science/Research
Classifier: Intended Audience :: Education
Classifier: Operating System :: MacOS :: MacOS X
Classifier: Operating System :: Microsoft :: Windows
Classifier: Operating System :: POSIX
Classifier: Programming Language :: Python :: 3
Classifier: Programming Language :: Python :: 3.7
Classifier: Programming Language :: Python :: 3.8
Classifier: Programming Language :: Python :: 3.9
Classifier: Programming Language :: Python :: 3.10
Classifier: Programming Language :: Python :: 3.11
Requires-Python: >=3.7
License-File: LICENSE.md
Requires-Dist: click
Requires-Dist: ipython>=7.1
Requires-Dist: nbconvert<7.0,>=6.0
Requires-Dist: jinja2>=3.0
Requires-Dist: ipython-genutils>=0.1
Requires-Dist: pyyaml>=5
Requires-Dist: cerberus>=1.1
Requires-Dist: lxml_html_clean
Provides-Extra: docs
Requires-Dist: sphinx==5.1.1; extra == "docs"
Requires-Dist: sphinx_rtd_theme==1.0.0; extra == "docs"
Provides-Extra: test
Requires-Dist: pytest; extra == "test"
Requires-Dist: tox; extra == "test"
Requires-Dist: webdriver-manager; extra == "test"
Requires-Dist: selenium; extra == "test"
Requires-Dist: pandas; extra == "test"
Requires-Dist: ipykernel; extra == "test"
Provides-Extra: dev
Requires-Dist: build; extra == "dev"
Requires-Dist: jupyter; extra == "dev"
Requires-Dist: ipykernel; extra == "dev"
Requires-Dist: pandas; extra == "dev"
Requires-Dist: matplotlib; extra == "dev"
Requires-Dist: seaborn; extra == "dev"
Requires-Dist: pip-tools; extra == "dev"
Requires-Dist: black; extra == "dev"
Requires-Dist: isort; extra == "dev"
Requires-Dist: pylint; extra == "dev"
Requires-Dist: autoflake; extra == "dev"
Requires-Dist: pre-commit; extra == "dev"
Requires-Dist: pretty-jupyter[docs]; extra == "dev"
Requires-Dist: pretty-jupyter[test]; extra == "dev"
Provides-Extra: all
Requires-Dist: pretty-jupyter[dev]; extra == "all"
